methodazure/__init__.py
methodazure/core/__init__.py
methodazure/core/datetime_utils.py
methodazure/core/pydantic_utilities.py
methodazure/core/serialization.py
methodazure/py.typed
methodazure/resources/__init__.py
methodazure/resources/azure/__init__.py
methodazure/resources/azure/resource_group.py
methodazure/resources/azure/subresource.py
methodazure/resources/iam/__init__.py
methodazure/resources/iam/iam_report.py
methodazure/resources/iam/permission.py
methodazure/resources/iam/principal_type.py
methodazure/resources/iam/role_assignment.py
methodazure/resources/iam/role_definition.py
methodazure/resources/interface/__init__.py
methodazure/resources/interface/interface_ip_configuration.py
methodazure/resources/interface/network_interface.py
methodazure/resources/interface/public_ip_address.py
methodazure/resources/interface/public_ip_address_dns_settings.py
methodazure/resources/interface/subnet.py
methodazure/resources/interface/transport_protocol.py
methodazure/resources/loadbalancer/__init__.py
methodazure/resources/loadbalancer/backend_address_pool.py
methodazure/resources/loadbalancer/load_balancer.py
methodazure/resources/loadbalancer/load_balancer_backend_address.py
methodazure/resources/loadbalancer/load_balancer_backend_address_admin_state.py
methodazure/resources/loadbalancer/load_balancer_report.py
methodazure/resources/loadbalancer/load_balancer_sku.py
methodazure/resources/loadbalancer/load_balancer_sku_name.py
methodazure/resources/loadbalancer/load_balancer_sku_tier.py
methodazure/resources/loadbalancer/load_balancing_rule.py
methodazure/resources/loadbalancer/nat_rule_port_mapping.py
methodazure/resources/loadbalancer/sync_mode.py
methodazure-0.0.16.dist-info/METADATA
methodazure-0.0.16.dist-info/WHEEL
methodazure-0.0.16.dist-info/RECORD
